file_organizer/__init__.py
file_organizer/cli.py
flm_file_organizer-0.1.0.dist-info/entry_points.txt
flm_file_organizer-0.1.0.dist-info/LICENSE
flm_file_organizer-0.1.0.dist-info/METADATA
flm_file_organizer-0.1.0.dist-info/WHEEL
flm_file_organizer-0.1.0.dist-info/RECORD
