Metadata-Version: 2.3
Name: flm-file-organizer
Version: 0.1.0
Summary: A file organizer for your folder
Author: Francisco Mota
Author-email: franciscolmota@outlook.com
Requires-Python: >=3.13
Classifier: Programming Language :: Python :: 3
Classifier: Programming Language :: Python :: 3.13
Requires-Dist: questionary (>=2.1.0,<3.0.0)
